{"name":"New account deposit with accountNo blank","id":"stories/create_customer_account_and_use_banking_services/account_can_deposit.story;New account deposit with accountNo blank","testSteps":[{"number":1,"description":"New account deposit with accountNo blank #1: {userId\u003dmngr91821, password\u003dudaneqE, accountNo\u003d, amount\u003d3000000, description\u003dthang 4, alertText\u003dplease fill all fields}","duration":9911,"startTime":"2017-08-14T16:26:39.160+07:00[Asia/Ho_Chi_Minh]","precondition":false,"children":[{"number":2,"description":"Given User login with \"{mngr91821}\" and \"{udaneqE}\" successfully","duration":6168,"startTime":"2017-08-14T16:26:39.161+07:00[Asia/Ho_Chi_Minh]","screenshots":[{"screenshot":"4966cf4b318a813ef0bed3fe07fcb7537ff212d784341a07354dbaf77e71b88f.png"}],"result":"SUCCESS","precondition":false,"children":[{"number":3,"description":"Open guru99 home page","duration":3342,"startTime":"2017-08-14T16:26:39.176+07:00[Asia/Ho_Chi_Minh]","screenshots":[{"screenshot":"871657ed8e462616edb616a9c39e29a1ea87f1958be3801a2e8e84a6a2e5ad9c.png"}],"result":"SUCCESS","precondition":false},{"number":4,"description":"Login to guru99: mngr91821, udaneqE","duration":1869,"startTime":"2017-08-14T16:26:42.519+07:00[Asia/Ho_Chi_Minh]","screenshots":[{"screenshot":"871657ed8e462616edb616a9c39e29a1ea87f1958be3801a2e8e84a6a2e5ad9c.png"},{"screenshot":"1082ab86d1d874bc32597b6008f2e46a6aee5aa781c2b8c12e33ee2ed8872e65.png"}],"result":"SUCCESS","precondition":false},{"number":5,"description":"Verify user login successfully","duration":650,"startTime":"2017-08-14T16:26:44.389+07:00[Asia/Ho_Chi_Minh]","screenshots":[{"screenshot":"53beaa5719181cac37721d0ef8ef9869faf4f76dfad6dab5ce8570ba3adceb5c.png"},{"screenshot":"0ace01d6cdb667316e2ae668157c3b57d69d1aa0dceb298dbc7255642eb286ef.png"}],"result":"SUCCESS","precondition":false}]},{"number":6,"description":"And New account want to deposit","duration":1907,"startTime":"2017-08-14T16:26:45.329+07:00[Asia/Ho_Chi_Minh]","screenshots":[{"screenshot":"a24b9537bfb74fb28bde8b64352973e71bd8bd9296048d2deaa0f714f0aeabf3.png"},{"screenshot":"4a9d6c33d453f417809e14df5fb3d3fdb2d61e30f78b2fff6bb1d5df76f2c452.png"}],"result":"SUCCESS","precondition":false,"children":[{"number":7,"description":"Open deposit page","duration":1320,"startTime":"2017-08-14T16:26:45.642+07:00[Asia/Ho_Chi_Minh]","screenshots":[{"screenshot":"a5bfb72cb7604b93d4c3b62b827afee1d61b44cbbe7d90bdce1d818e7a12c026.png"},{"screenshot":"4a9d6c33d453f417809e14df5fb3d3fdb2d61e30f78b2fff6bb1d5df76f2c452.png"}],"result":"SUCCESS","precondition":false}]},{"number":8,"description":"When New account input \"{}\" and \"{3000000}\" and \"{thang 4}\" and submit","duration":1806,"startTime":"2017-08-14T16:26:47.237+07:00[Asia/Ho_Chi_Minh]","screenshots":[{"screenshot":"4a9d6c33d453f417809e14df5fb3d3fdb2d61e30f78b2fff6bb1d5df76f2c452.png"}],"result":"SUCCESS","precondition":false,"children":[{"number":9,"description":"Input deposit info: , 3000000, thang 4","duration":931,"startTime":"2017-08-14T16:26:47.498+07:00[Asia/Ho_Chi_Minh]","screenshots":[{"screenshot":"4a9d6c33d453f417809e14df5fb3d3fdb2d61e30f78b2fff6bb1d5df76f2c452.png"},{"screenshot":"0704811b16fe6a6ce022923cb1ca46208c94a250cd439b97e5012a7f47ba3f1b.png"}],"result":"SUCCESS","precondition":false},{"number":10,"description":"Click on submit button","duration":608,"startTime":"2017-08-14T16:26:48.430+07:00[Asia/Ho_Chi_Minh]","screenshots":[{"screenshot":"0704811b16fe6a6ce022923cb1ca46208c94a250cd439b97e5012a7f47ba3f1b.png"}],"result":"SUCCESS","precondition":false}]},{"number":11,"description":"Then Alert \"{please fill all fields}\" is displayed","duration":27,"startTime":"2017-08-14T16:26:49.044+07:00[Asia/Ho_Chi_Minh]","result":"SUCCESS","precondition":false}]}],"userStory":{"id":"account_can_deposit","storyName":"Account can deposit","path":"stories/create_customer_account_and_use_banking_services/account_can_deposit.story","narrative":"","type":"story"},"featureTag":{"name":"Create customer account and use banking services/Account can deposit","type":"story"},"title":"New account deposit with accountNo blank","tags":[{"name":"Create customer account and use banking services","type":"feature"},{"name":"Create customer account and use banking services/Account can deposit","type":"story"}],"startTime":"2017-08-14T16:26:39.157+07:00[Asia/Ho_Chi_Minh]","duration":9970,"projectKey":"","dataTable":{"headers":["userId","password","accountNo","amount","description","alertText"],"rows":[{"values":["mngr91821","udaneqE","","3000000","thang 4","please fill all fields"],"result":"SUCCESS"}],"predefinedRows":true,"scenarioOutline":"Given User login with \"\u003cuserId\u003e\" and \"\u003cpassword\u003e\" successfully\nAnd New account want to deposit\nWhen New account input \"\u003caccountNo\u003e\" and \"\u003camount\u003e\" and \"\u003cdescription\u003e\" and submit\nThen Alert \"\u003calertText\u003e\" is displayed\n","dataSetDescriptors":[{"startRow":0,"rowCount":0}]},"manual":false,"testSource":"JBehave","result":"SUCCESS"}